atlan_airflow_plugin/__init__.py
atlan_airflow_plugin/hooks/__init__.py
atlan_airflow_plugin/hooks/atlan_hook.py
atlan_airflow_plugin/lineage/__init__.py
atlan_airflow_plugin/lineage/atlan.py
atlan_airflow_plugin/lineage/backend.py
atlan_airflow_plugin/lineage/assets/__init__.py
atlan_airflow_plugin/lineage/assets/atlan_asset.py
atlan_airflow_plugin/lineage/assets/atlan_process.py
atlan_airflow_plugin/lineage/assets/atlan_table.py
atlan_airflow_plugin/operators/__init__.py
atlan_airflow_plugin/operators/bm_operator.py
atlan_airflow_plugin/utils/__init__.py
atlan_airflow_plugin/utils/check_exception.py
atlan_airflow_plugin-0.0.1.dist-info/METADATA
atlan_airflow_plugin-0.0.1.dist-info/WHEEL
atlan_airflow_plugin-0.0.1.dist-info/top_level.txt
atlan_airflow_plugin-0.0.1.dist-info/RECORD
